MANIFEST.in
README.rst
pyproject.toml
setup.cfg
setup.py
moni_auth/__init__.py
moni_auth/apps.py
moni_auth/authenticators.py
moni_auth/exceptions.py
moni_auth/mixins.py
moni_auth/models.py
moni_auth/permissions.py
moni_auth/service.py
moni_auth/signals.py
moni_auth/tests.py
moni_auth/urls.py
moni_auth/utils.py
moni_auth/views.py
moni_auth.egg-info/PKG-INFO
moni_auth.egg-info/SOURCES.txt
moni_auth.egg-info/dependency_links.txt
moni_auth.egg-info/requires.txt
moni_auth.egg-info/top_level.txt