Metadata-Version: 2.1
Name: moni-auth
Version: 1.0.7
Summary: Django app to integrate with the centralized Moni authentication system
Home-page: https://www.example.com/
Author: Lorenzo Fabro
Author-email: lorenzo.fabro@moni.com.ar
Classifier: Environment :: Web Environment
Classifier: Framework :: Django
Classifier: Intended Audience :: Developers
Classifier: License :: OSI Approved :: BSD License
Classifier: Operating System :: OS Independent
Classifier: Programming Language :: Python
Classifier: Programming Language :: Python :: 3
Classifier: Programming Language :: Python :: 3 :: Only
Classifier: Programming Language :: Python :: 3.8
Classifier: Programming Language :: Python :: 3.9
Classifier: Topic :: Internet :: WWW/HTTP
Classifier: Topic :: Internet :: WWW/HTTP :: Dynamic Content
Requires-Python: >=3.7
